torchql/__init__.py
torchql/database.py
torchql/database_lazy.py
torchql/query.py
torchql/table.py
torchql/table_lazy.py
torchql/utils.py
torchql-0.0.6.dist-info/METADATA
torchql-0.0.6.dist-info/WHEEL
torchql-0.0.6.dist-info/top_level.txt
torchql-0.0.6.dist-info/RECORD
